presubmit/__init__.py
presubmit-0.1.0.dist-info/licenses/LICENSE
presubmit-0.1.0.dist-info/METADATA
presubmit-0.1.0.dist-info/WHEEL
presubmit-0.1.0.dist-info/top_level.txt
presubmit-0.1.0.dist-info/RECORD
